micropython_sht20/__init__.py
micropython_sht20/sht20.py
micropython_sht20-0.1.0.dist-info/LICENSE
micropython_sht20-0.1.0.dist-info/METADATA
micropython_sht20-0.1.0.dist-info/WHEEL
micropython_sht20-0.1.0.dist-info/top_level.txt
micropython_sht20-0.1.0.dist-info/RECORD
