Metadata-Version: 2.1
Name: micropython-sht20
Version: 0.1.0
Summary: MicroPython Driver for the Sensirion SHT20 Temperature Sensor
Author-email: JDM <xxyx@mailmeto.mozmail.com>
License: MIT
Project-URL: Homepage, https://github.com/jposada202020/MicroPython_SHT20
Keywords: sensor,micropython,sht20,temperature,sensirion,driver,sensor,micropython
Classifier: Intended Audience :: Developers
Classifier: Topic :: Software Development :: Libraries
Classifier: Topic :: Software Development :: Embedded Systems
Classifier: Topic :: System :: Hardware
Classifier: License :: OSI Approved :: MIT License
Classifier: Programming Language :: Python :: Implementation :: MicroPython
License-File: LICENSE
